README.md
setup.py
gym_foo/__init__.py
gym_foo.egg-info/PKG-INFO
gym_foo.egg-info/SOURCES.txt
gym_foo.egg-info/dependency_links.txt
gym_foo.egg-info/requires.txt
gym_foo.egg-info/top_level.txt
test/test.py