Metadata-Version: 1.2
Name: gym-foo
Version: 0.1
Summary: GCPDS: gym-foo
Home-page: UNKNOWN
Author: Yeison Cardona
Author-email: yeisoneng@gmail.com
Maintainer: Yeison Cardona
Maintainer-email: yeisoneng@gmail.com
License: BSD License
Download-URL: https://bitbucket.org/gcpds/gym_foo/downloads/
Platform: UNKNOWN
